{
  "lesson": 44,
  "source": "Minna no Nihongo II - Bản dịch và giải thích ngữ pháp (Sơ cấp 2), tr.135-136",
  "status": "REVIEW_REQUIRED",
  "vocab": [
    {
      "w": "なきますⅠ",
      "k": "泣きます",
      "m": "khóc"
    },
    {
      "w": "わらいますⅠ",
      "k": "笑います",
      "m": "cười"
    },
    {
      "w": "かわきますⅠ",
      "k": "乾きます",
      "m": "khô"
    },
    {
      "w": "ぬれますⅡ",
      "k": "",
      "m": "ướt"
    },
    {
      "w": "すべりますⅠ",
      "k": "滑ります",
      "m": "trượt"
    },
    {
      "w": "おきますⅡ [じこが～]",
      "k": "起きます [事故が～]",
      "m": "xảy ra [tai nạn ~]"
    },
    {
      "w": "ちょうせつしますⅢ",
      "k": "調節します",
      "m": "điều tiết, điều chỉnh"
    },
    {
      "w": "あんぜん[な]",
      "k": "安全[な]",
      "m": "an toàn"
    },
    {
      "w": "ていねい[な]",
      "k": "丁寧[な]",
      "m": "lịch sự, cẩn thận"
    },
    {
      "w": "こまかい",
      "k": "細かい",
      "m": "chi tiết, tỉ mỉ, nhỏ"
    },
    {
      "w": "こい",
      "k": "濃い",
      "m": "nồng, đậm"
    },
    {
      "w": "うすい",
      "k": "薄い",
      "m": "nhạt"
    },
    {
      "w": "くうき",
      "k": "空気",
      "m": "không khí"
    },
    {
      "w": "なみだ",
      "k": "涙",
      "m": "nước mắt"
    },
    {
      "w": "わしょく",
      "k": "和食",
      "m": "món ăn Nhật"
    },
    {
      "w": "ようしょく",
      "k": "洋食",
      "m": "món ăn Âu Mỹ"
    },
    {
      "w": "おかず",
      "k": "",
      "m": "thức ăn"
    },
    {
      "w": "りょう",
      "k": "量",
      "m": "lượng"
    },
    {
      "w": "－ばい",
      "k": "－倍",
      "m": "－ lần"
    },
    {
      "w": "はんぶん",
      "k": "半分",
      "m": "một nửa"
    },
    {
      "w": "シングル",
      "k": "",
      "m": "phòng đơn (1 giường)"
    },
    {
      "w": "ツイン",
      "k": "",
      "m": "phòng đôi (2 giường)"
    },
    {
      "w": "たんす",
      "k": "",
      "m": "tủ đựng quần áo"
    },
    {
      "w": "せんたくもの",
      "k": "洗濯物",
      "m": "quần áo giặt"
    },
    {
      "w": "りゆう",
      "k": "理由",
      "m": "lý do"
    }
  ],
  "expressions": [
    {
      "w": "どう なさいますか。",
      "m": "Anh/Chị định như thế nào?"
    },
    {
      "w": "カット",
      "m": "cắt tóc"
    },
    {
      "w": "シャンプー",
      "m": "gội đầu"
    },
    {
      "w": "どういうふうに なさいますか。",
      "m": "Anh/Chị định ~ như thế nào?"
    },
    {
      "w": "ショート",
      "m": "kiểu ngắn"
    },
    {
      "w": "～みたいに して ください。",
      "m": "Hãy cắt như ~."
    },
    {
      "w": "これで よろしいでしょうか。",
      "m": "Thế này đã được chưa ạ?"
    },
    {
      "w": "[どうも] お疲れさまでした[おつかれさまでした]。",
      "m": "Cám ơn anh/chị."
    },
    {
      "w": "嫌がります[いやがります]Ⅰ",
      "m": "không thích, tỏ thái độ không thích"
    },
    {
      "w": "また",
      "m": "thêm nữa"
    },
    {
      "w": "順序[じゅんじょ]",
      "m": "thứ tự"
    },
    {
      "w": "表現[ひょうげん]",
      "m": "cách nói, cách diễn đạt"
    },
    {
      "w": "例えば[たとえば]",
      "m": "ví dụ"
    },
    {
      "w": "別れます[わかれます]Ⅱ",
      "m": "chia tay, từ biệt"
    },
    {
      "w": "これら",
      "m": "những cái này"
    },
    {
      "w": "縁起が 悪い[えんぎが わるい]",
      "m": "không may, không lành"
    }
  ]
}